purple_plan.cpython-310-x86_64-linux-gnu.so
purple_plan-0.1.7.dist-info/METADATA
purple_plan-0.1.7.dist-info/WHEEL
purple_plan-0.1.7.dist-info/top_level.txt
purple_plan-0.1.7.dist-info/RECORD
