Metadata-Version: 2.1
Name: purple-plan
Version: 0.1.7
Summary: PURPLE Python API
Home-page: https://www.black-sat.org
Author: Nicola Gigante
Author-email: nicola.gigante@unibz.it
License: MIT
Platform: UNKNOWN
Classifier: License :: OSI Approved :: MIT License
Classifier: Topic :: Scientific/Engineering :: Artificial Intelligence
Requires-Dist: black-sat
